lotterytickets/__init__.py
lotterytickets/lotterytickets.py
lotterytickets-2.0.2.dist-info/LICENSE
lotterytickets-2.0.2.dist-info/METADATA
lotterytickets-2.0.2.dist-info/WHEEL
lotterytickets-2.0.2.dist-info/top_level.txt
lotterytickets-2.0.2.dist-info/RECORD
