Metadata-Version: 2.1
Name: lotterytickets
Version: 2.0.2
Summary: 彩票一体机（lotterytickets-Including）
Home-page: https://github.com/lichenyichay/lotterytickets-Including/
Author: Chay
Author-email: chay <lichenyi_2020@qq.com>
Project-URL: Homepage, https://github.com/lichenyichay/lotterytickets-Including/
Project-URL: Issues, https://github.com/lichenyichay/lotterytickets-Including/issues
Classifier: Programming Language :: Python :: 3
Classifier: License :: OSI Approved :: MIT License
Classifier: Operating System :: OS Independent
Requires-Python: >=3.5
License-File: LICENSE
